fc_xd_bigdata3.py
fc_zyx-1.0.dist-info/METADATA
fc_zyx-1.0.dist-info/WHEEL
fc_zyx-1.0.dist-info/top_level.txt
fc_zyx-1.0.dist-info/RECORD
