Metadata-Version: 2.1
Name: fc-zyx
Version: 1.0
Summary: 大数据3
Home-page: UNKNOWN
Author: 大数据3
Author-email: fc@bigdata.com
License: UNKNOWN
Platform: UNKNOWN
